happtiq_commons_google_cloud/__init__.py
happtiq_commons_google_cloud/auth_service.py
happtiq_commons_google_cloud/gcs_api_service.py
happtiq_commons_google_cloud/input_parser_service.py
happtiq_commons_google_cloud/logging_utils.py
happtiq_commons_google_cloud/pubsub_api_service.py
happtiq_commons_google_cloud/secret_manager_api_service.py
happtiq_commons_google_cloud-2.0.1.dist-info/METADATA
happtiq_commons_google_cloud-2.0.1.dist-info/WHEEL
happtiq_commons_google_cloud-2.0.1.dist-info/top_level.txt
happtiq_commons_google_cloud-2.0.1.dist-info/RECORD
